{"/m/0q96": {"top": "                           query  value\n0                          labor    100\n1                         labour     40\n2                    labor party     39\n3                        liberal     33\n4               australian labor     13\n5               labour australia     12\n6                   labour party     12\n7                     one nation     11\n8          labor party australia     11\n9                  liberal party     10\n10        australian labor party      9\n11                           alp      9\n12              labor government      8\n13        labour party australia      7\n14                      albanese      6\n15              one nation party      5\n16                        greens      5\n17       australian labour party      4\n18      labor party of australia      4\n19                    labor news      4\n20                  labor greens      4\n21                pauline hanson      3\n22                labor policies      3\n23  labor government cgt changes      3\n24               labor candidate      3", "rising": "                                             query   value\n0                                   pauline hanson  228650\n1                         fire the liar one nation  136650\n2                                 labor fundraiser   98950\n3                      prime minister of australia   95500\n4                                    jacinta allen   71050\n5   when is the next federal election in australia   62800\n6                                   labor donation   60500\n7                           labor cgt changes 2027   48350\n8                                       labor poll   34200\n9                                    fire the liar   10300\n10                                     mark butler    9850\n11                                one nation party     250\n12                    labor government cgt changes     160\n13                                      one nation     100\n14                                labor government      70\n15                                      labor news      60\n16                                    labor greens      40\n17                                 labour or labor      40"}, "/m/04p4r": {"top": "                             query  value\n0                          liberal    100\n1                    liberal party     77\n2                liberal australia     23\n3          liberal party australia     18\n4                   liberal leader     14\n5             liberal party leader     12\n6                            labor      8\n7       liberal party of australia      8\n8                       one nation      8\n9                      labor party      7\n10          liberal party victoria      7\n11                          labour      7\n12         leader of liberal party      6\n13        australian liberal party      6\n14                one nation party      5\n15                    labour party      5\n16  liberal party leader australia      5\n17     leader of the liberal party      4\n18                liberal policies      4\n19         liberal party president      4\n20           federal liberal party      4\n21        liberal leader australia      4\n22                 liberal leaders      4\n23                        liberals      4\n24           labor party australia      3", "rising": "                                             query  value\n0                            labour party policies  98350\n1                       federal election australia  70350\n2                           colleen harkin liberal  65550\n3                                labour vs liberal  64150\n4                     australian political parties  35350\n5                                  greens policies  14200\n6                          pauline hanson policies  10900\n7                                     peter dutton   8700\n8   when is the next federal election in australia   2900\n9                                    teena mcqueen   2700\n10                         liberal party president   1400\n11                             one nation policies    170\n12                                     tony abbott    160\n13          who is the leader of the liberal party    150\n14                        liberal party membership    140\n15                  who is leader of liberal party    110\n16                                liberal policies    100\n17                                      one nation     90\n18                                one nation party     80\n19              who is the leader of liberal party     80\n20                           labor party australia     80\n21                                           labor     70\n22                          liberal party policies     70\n23                  liberal party leader australia     60\n24                                     labor party     60"}, "/m/0171c7": {"top": "                         query  value\n0                       greens    100\n1                   the greens     40\n2             australia greens     17\n3            australian greens     16\n4             the greens party     10\n5                 labor greens      9\n6                greens leader      9\n7         the greens australia      8\n8                   one nation      8\n9                        labor      7\n10      greens party australia      6\n11             greens policies      6\n12               greens policy      5\n13                     liberal      5\n14           the greens leader      5\n15              greens senator      4\n16     australian greens party      4\n17            leader of greens      4\n18        leader of the greens      3\n19         the greens policies      3\n20     greens leader australia      3\n21               liberal party      2\n22         greens party leader      2\n23             labour policies      2\n24  the greens political party      2", "rising": "                            query   value\n0          greens leader victoria  170350\n1                     greens smsf   64900\n2                    lidia thorpe   13250\n3                  greens tapware    5900\n4   greens senator mehreen faruqi    3650\n5                       socialism    3000\n6                 greens policies     200\n7      the greens political party     150\n8             the greens policies     120\n9                  larissa waters      70\n10                   labor greens      50\n11                  greens policy      50\n12                     one nation      40"}, "/m/0l8lg": {"top": "                        query  value\n0                  one nation    100\n1        one nation australia     11\n2            one nation party      9\n3         one nation election      9\n4         one nation victoria      7\n5              pauline hanson      7\n6         one nation policies      7\n7               fire the liar      6\n8    one nation fire the liar      6\n9   one nation pauline hanson      6\n10         what is one nation      5\n11                     farrer      3\n12             one nation win      3\n13          one nation policy      3\n14            one nation news      3\n15         one nation polling      3\n16          one nation farrer      3\n17           one nation seats      3\n18       one nation donations      3\n19           one nation polls      2\n20      one nation fundraiser      2\n21          one nation leader      2\n22            one nation poll      2\n23      one nation candidates      2\n24              liberal party      2", "rising": "                                             query   value\n0                         one nation fire the liar  466150\n1               one nation lower house projections   82600\n2                                    fire the lair   49450\n3                             donate to one nation   44350\n4               one nation donations fire the liar   40200\n5                    what are one nations policies   37600\n6                                one nation rapist   36500\n7                         fire the lair one nation   33100\n8            will one nation win the next election   29700\n9                      how to donate to one nation   27900\n10                  how much has one nation raised   26300\n11                  can one nation form government   24800\n12              what are pauline hanson's policies   23500\n13  when is the next federal election in australia   22700\n14                          jason virgo one nation   22050\n15                          one nation fund raiser   20750\n16                           one nation gas policy   18550\n17                           farrer electorate map   17950\n18        one nation farrer by-election prediction   17100\n19                      one nation abortion policy   14800\n20                        pauline hansons daughter   14200\n21                            one nation donations    1650\n22                                   fire the liar    1200\n23                           one nation fundraiser     250\n24                                          farrer     150"}, "/m/0j3dlg7": {"top": "                           query  value\n0  animal justice party victoria    100", "rising": null}, "/m/04zy__7": {"top": null, "rising": null}, "/m/09g1_s": {"top": null, "rising": null}}