{"/m/0q96": {"top": "                              query  value\n0                             labor    100\n1                            labour     47\n2                       labor party     35\n3                           liberal     34\n4                  labour australia     15\n5                      labour party     13\n6                               alp     12\n7                     liberal party     10\n8            australian labor party      9\n9             labor party australia      8\n10                 labor government      7\n11           labour party australia      6\n12                       one nation      6\n13                           greens      4\n14          australian labour party      4\n15                  labor candidate      4\n16                  labor or labour      4\n17               is albanese labour      3\n18                    alp australia      3\n19                        labor mps      3\n20               labor party leader      3\n21                labour vs liberal      3\n22                     alp victoria      3\n23       liberal party of australia      2\n24  tammy tyrrell joins labor party      2", "rising": "                              query   value\n0   tammy tyrrell joins labor party  148050\n1                    labor policies  139600\n2            labor party membership   82000\n3                   labor death tax   17050\n4      is labor party left or right   13800\n5                       tony abbott   11450\n6                      jim chalmers    9100\n7   is chris minns labor or liberal    8750\n8                        labor poll    6500\n9                      angus taylor    5700\n10                   pauline hanson     250\n11               is albanese labour     200\n12                     alp victoria     180\n13                        labor mps     160\n14                    alp australia     140\n15                  labor or labour     120"}, "/m/04p4r": {"top": "                             query  value\n0                          liberal    100\n1                    liberal party     81\n2                the liberal party     28\n3                liberal australia     24\n4          liberal party australia     20\n5                   liberal leader     15\n6             liberal party leader     11\n7       liberal party of australia      9\n8                           labour      7\n9         australian liberal party      7\n10          liberal party victoria      6\n11                     labor party      5\n12         leader of liberal party      5\n13                    labour party      5\n14                    angus taylor      4\n15                one nation party      4\n16                      one nation      4\n17                     liberal vic      4\n18     leader of the liberal party      4\n19          liberal party policies      3\n20           federal liberal party      3\n21         liberal party president      3\n22                        liberals      3\n23  liberal party leader australia      3\n24          labour party australia      2", "rising": "                             query   value\n0          liberal party president  273500\n1        tony abbott liberal party  137850\n2                 labor vs liberal  125600\n3            head of liberal party   48950\n4              one nation policies   46150\n5                       tony abbot   28200\n6                 alexander downer    6600\n7                       john olsen    5400\n8              tony abbott liberal     550\n9    liberal party election review     300\n10      president of liberal party     200\n11                    julie bishop     170\n12       liberal opposition leader     140\n13                     tony abbott      90\n14  president of the liberal party      90\n15                     liberal vic      70\n16                     john howard      60\n17          liberal party policies      60\n18                     labor party      60\n19          labour party australia      50\n20               the liberal party      40\n21                          labour      40"}, "/m/0171c7": {"top": "                      query  value\n0                    greens    100\n1                the greens     35\n2          greens australia     16\n3         australian greens     14\n4          the greens party      8\n5             greens leader      8\n6                one nation      6\n7                   liberal      5\n8                     labor      5\n9          leader of greens      5\n10          greens policies      4\n11           greens senator      4\n12     leader of the greens      3\n13                greens mp      3\n14            liberal party      3\n15      the greens policies      3\n16        greens candidates      2\n17  greens negative gearing      2\n18           pauline hanson      2\n19      one nation policies      2\n20         david shoebridge      1\n21          greens senators      1\n22               adam bandt      1\n23         anthony albanese      0\n24           greens tapware      0", "rising": "                     query   value\n0           pauline hanson  164000\n1               adam bandt   76550\n2         anthony albanese   18750\n3           greens tapware    2600\n4  greens negative gearing     130\n5               one nation      80"}, "/m/0l8lg": {"top": "                                query  value\n0                          one nation    100\n1                one nation australia     15\n2                 one nation election     14\n3                       one nation sa      9\n4                    one nation seats      9\n5                    one nation party      8\n6                 one nation victoria      8\n7                      one nation win      7\n8          one nation south australia      6\n9                 one nation policies      6\n10                     pauline hanson      5\n11                             farrer      5\n12                  one nation farrer      5\n13                 what is one nation      5\n14                        sa election      4\n15             one nation sa election      4\n16          one nation pauline hanson      4\n17                    news one nation      4\n18                 one nation polling      4\n19           south australia election      3\n20                  one nation policy      3\n21                   one nation polls      2\n22  how many seats did one nation win      2\n23                    one nation poll      2\n24            david farley one nation      2", "rising": "                                             query   value\n0                how many seats did one nation win  186750\n1                              sa election results  159600\n2                   sa election results one nation  139050\n3                 south australia election results  107900\n4                                one nation rapist   60600\n5                               nepean by election   47300\n6                   what does one nation stand for   40400\n7                           jason virgo one nation   38750\n8                south australian election results   34800\n9               did one nation win any seats in sa   34400\n10                      one nation popularity poll   34250\n11                      farrer by election results   18600\n12                               gay one nation mp   18000\n13  when is the next federal election in australia   16100\n14                           farrer electorate map   14650\n15                          david paton one nation   14050\n16                  one nation immigration polling    8700\n17                            stafford by election    8600\n18                   one nation mp south australia    6850\n19                                     sa election    2450\n20                                   one nation sa    1600\n21                          one nation sa election     900\n22                                    david farley     850\n23                        south australia election     650\n24                               one nation farrer     650"}, "/m/0j3dlg7": {"top": "                           query  value\n0  animal justice party victoria    100", "rising": null}, "/m/04zy__7": {"top": null, "rising": null}, "/m/09g1_s": {"top": null, "rising": null}}