{
  "ALP": {
    "top": [
      {
        "query": "labor",
        "value": 100
      },
      {
        "query": "labour",
        "value": 54
      },
      {
        "query": "labor party",
        "value": 45
      },
      {
        "query": "liberal",
        "value": 36
      },
      {
        "query": "labor australia",
        "value": 27
      },
      {
        "query": "australian labor",
        "value": 21
      },
      {
        "query": "labour australia",
        "value": 18
      },
      {
        "query": "labour party",
        "value": 16
      },
      {
        "query": "alp",
        "value": 15
      },
      {
        "query": "australian labor party",
        "value": 15
      },
      {
        "query": "liberal party",
        "value": 13
      },
      {
        "query": "liberal or labour",
        "value": 12
      },
      {
        "query": "labor party australia",
        "value": 12
      },
      {
        "query": "labor government",
        "value": 8
      },
      {
        "query": "one nation",
        "value": 7
      },
      {
        "query": "labour party australia",
        "value": 7
      },
      {
        "query": "australian labour party",
        "value": 7
      },
      {
        "query": "liberal party australia",
        "value": 6
      },
      {
        "query": "greens",
        "value": 5
      },
      {
        "query": "labor or labour",
        "value": 4
      },
      {
        "query": "labor policies",
        "value": 4
      },
      {
        "query": "liberal vs labour",
        "value": 4
      },
      {
        "query": "alp party",
        "value": 4
      },
      {
        "query": "labor vs liberal",
        "value": 3
      },
      {
        "query": "one nation party",
        "value": 3
      }
    ],
    "rising": [
      {
        "query": "alp membership",
        "value": 39750
      },
      {
        "query": "one nation policies",
        "value": 250
      },
      {
        "query": "sa election results",
        "value": 190
      },
      {
        "query": "one nation party",
        "value": 80
      },
      {
        "query": "one nation",
        "value": 70
      },
      {
        "query": "labor policies",
        "value": 70
      },
      {
        "query": "liberal policies",
        "value": 70
      },
      {
        "query": "labor or labour",
        "value": 60
      },
      {
        "query": "liberal vs labour",
        "value": 60
      },
      {
        "query": "greens",
        "value": 50
      },
      {
        "query": "labor vs liberal",
        "value": 50
      },
      {
        "query": "alp australia",
        "value": 40
      },
      {
        "query": "alp party",
        "value": 40
      }
    ]
  },
  "LIB": {
    "top": [
      {
        "query": "liberal",
        "value": 100
      },
      {
        "query": "liberal party",
        "value": 65
      },
      {
        "query": "liberal leader",
        "value": 15
      },
      {
        "query": "liberal party australia",
        "value": 14
      },
      {
        "query": "liberal party leader",
        "value": 11
      },
      {
        "query": "liberal party of australia",
        "value": 7
      },
      {
        "query": "australian liberal party",
        "value": 7
      },
      {
        "query": "angus taylor",
        "value": 6
      },
      {
        "query": "leader of liberal party",
        "value": 6
      },
      {
        "query": "one nation",
        "value": 4
      },
      {
        "query": "labor party",
        "value": 4
      },
      {
        "query": "leader of the liberal party",
        "value": 4
      },
      {
        "query": "liberal leader australia",
        "value": 4
      },
      {
        "query": "labour party",
        "value": 3
      },
      {
        "query": "one nation party",
        "value": 3
      },
      {
        "query": "liberal party review",
        "value": 2
      },
      {
        "query": "liberal immigration policy",
        "value": 1
      }
    ],
    "rising": [
      {
        "query": "angus taylor",
        "value": 800
      },
      {
        "query": "liberal immigration policy",
        "value": 300
      },
      {
        "query": "liberal party review",
        "value": 190
      },
      {
        "query": "one nation",
        "value": 50
      }
    ]
  },
  "GRN": {
    "top": [
      {
        "query": "greens",
        "value": 100
      },
      {
        "query": "the greens",
        "value": 44
      },
      {
        "query": "australia greens",
        "value": 21
      },
      {
        "query": "greens party",
        "value": 17
      },
      {
        "query": "australian greens",
        "value": 15
      },
      {
        "query": "the greens party",
        "value": 11
      },
      {
        "query": "the greens australia",
        "value": 10
      },
      {
        "query": "greens leader",
        "value": 9
      },
      {
        "query": "greens policies",
        "value": 7
      },
      {
        "query": "labor",
        "value": 6
      },
      {
        "query": "one nation",
        "value": 6
      },
      {
        "query": "liberal",
        "value": 6
      },
      {
        "query": "the greens leader",
        "value": 5
      },
      {
        "query": "greens policy",
        "value": 4
      },
      {
        "query": "labour",
        "value": 4
      },
      {
        "query": "leader of the greens",
        "value": 4
      },
      {
        "query": "how to vote greens",
        "value": 3
      },
      {
        "query": "labor party",
        "value": 3
      },
      {
        "query": "greens leader australia",
        "value": 2
      },
      {
        "query": "larissa waters",
        "value": 1
      },
      {
        "query": "greens immigration policy",
        "value": 0
      }
    ],
    "rising": [
      {
        "query": "how to vote greens",
        "value": 254350
      },
      {
        "query": "larissa waters",
        "value": 89650
      },
      {
        "query": "greens immigration policy",
        "value": 41750
      },
      {
        "query": "one nation",
        "value": 140
      },
      {
        "query": "greens policies",
        "value": 90
      },
      {
        "query": "liberal",
        "value": 70
      },
      {
        "query": "labour",
        "value": 50
      }
    ]
  },
  "PHON": {
    "top": [
      {
        "query": "one nation",
        "value": 100
      },
      {
        "query": "one nation sa",
        "value": 12
      },
      {
        "query": "one nation seats",
        "value": 10
      },
      {
        "query": "one nation party",
        "value": 8
      },
      {
        "query": "sa election",
        "value": 7
      },
      {
        "query": "sa election one nation",
        "value": 7
      },
      {
        "query": "one nation policies",
        "value": 6
      },
      {
        "query": "pauline hanson",
        "value": 5
      },
      {
        "query": "vote one nation",
        "value": 5
      },
      {
        "query": "one nation polling",
        "value": 5
      },
      {
        "query": "one nation pauline hanson",
        "value": 5
      },
      {
        "query": "one nation seats sa",
        "value": 5
      },
      {
        "query": "what is one nation",
        "value": 4
      },
      {
        "query": "one nation election results",
        "value": 4
      },
      {
        "query": "one nation news",
        "value": 4
      },
      {
        "query": "south australia election",
        "value": 4
      },
      {
        "query": "south australia election one nation",
        "value": 4
      },
      {
        "query": "one nation polls",
        "value": 3
      },
      {
        "query": "one nation victoria",
        "value": 3
      },
      {
        "query": "one nation sa results",
        "value": 3
      },
      {
        "query": "one nation candidates",
        "value": 3
      },
      {
        "query": "one nation party australia",
        "value": 2
      },
      {
        "query": "sa election results",
        "value": 2
      },
      {
        "query": "sa election results one nation",
        "value": 2
      },
      {
        "query": "sa election one nation seats",
        "value": 2
      }
    ],
    "rising": [
      {
        "query": "one nation seats sa",
        "value": 411250
      },
      {
        "query": "sa election results",
        "value": 211700
      },
      {
        "query": "sa election results one nation",
        "value": 202150
      },
      {
        "query": "one nation farrer",
        "value": 139800
      },
      {
        "query": "south australia election results",
        "value": 134750
      },
      {
        "query": "cory bernardi",
        "value": 88100
      },
      {
        "query": "did one nation win any seats",
        "value": 86300
      },
      {
        "query": "sa election results 2026 one nation",
        "value": 69800
      },
      {
        "query": "did one nation win any seats in sa",
        "value": 39150
      },
      {
        "query": "how many seats did one nation win in south australia",
        "value": 37850
      },
      {
        "query": "how many seats has one nation won in sa",
        "value": 19250
      },
      {
        "query": "jason virgo one nation",
        "value": 18250
      },
      {
        "query": "one nation sa results",
        "value": 2600
      },
      {
        "query": "sa election",
        "value": 2500
      },
      {
        "query": "sa election 2026",
        "value": 2000
      },
      {
        "query": "sa election one nation",
        "value": 1650
      },
      {
        "query": "how many seats did one nation win",
        "value": 1250
      },
      {
        "query": "south australia election one nation",
        "value": 1250
      },
      {
        "query": "sa election one nation seats",
        "value": 1150
      },
      {
        "query": "one nation sa",
        "value": 1050
      },
      {
        "query": "south australia election",
        "value": 950
      },
      {
        "query": "one nation election results",
        "value": 600
      },
      {
        "query": "one nation seats",
        "value": 250
      },
      {
        "query": "vote one nation",
        "value": 100
      },
      {
        "query": "one nation candidates",
        "value": 90
      }
    ]
  }
}